LICENSE.md
README.md
setup.cfg
setup.py
state_moseq/__init__.py
state_moseq/_version.py
state_moseq/hhmm_efficient.py
state_moseq/hhmm_standard.py
state_moseq/util.py
state_moseq/viz.py
state_moseq.egg-info/PKG-INFO
state_moseq.egg-info/SOURCES.txt
state_moseq.egg-info/dependency_links.txt
state_moseq.egg-info/requires.txt
state_moseq.egg-info/top_level.txt